CHANGELOG.md
LICENSE.txt
MANIFEST.in
README.md
setup.py
videodownloader/__init__.py
videodownloader/main.py
videodownloader.egg-info/PKG-INFO
videodownloader.egg-info/SOURCES.txt
videodownloader.egg-info/dependency_links.txt
videodownloader.egg-info/entry_points.txt
videodownloader.egg-info/top_level.txt
videodownloader/providers/__init__.py
videodownloader/providers/vimeo.py
videodownloader/providers/youtube.py