Metadata-Version: 1.0
Name: videodownloader
Version: 2.0.0
Summary: Python module and script for downloading video source files from the major online streaming sites (YouTube, Vimeo, etc.)
Home-page: http://github.com/JakeWharton/py-videodownloader
Author: Jake Wharton
Author-email: jakewharton@gmail.com
License: Apache License, Version 2.0
Keywords: youtube vimeo download streaming video save
Platform: UNKNOWN
Classifier: Development Status :: 5 - Production/Stable
Classifier: Intended Audience :: Developers
Classifier: License :: OSI Approved :: Apache Software License
Classifier: Natural Language :: English
Classifier: Operating System :: OS Independent
Classifier: Programming Language :: Python
Classifier: Programming Language :: Python :: 2
Classifier: Topic :: Internet
Classifier: Topic :: Internet :: WWW/HTTP
Classifier: Topic :: Multimedia :: Video
Classifier: Topic :: Utilities
